polymarket_gamma_sdk-1.0.0.dist-info/licenses/LICENSE
py_gamma_sdk/__init__.py
py_gamma_sdk/client.py
py_gamma_sdk/constants.py
py_gamma_sdk/exceptions.py
py_gamma_sdk/models.py
polymarket_gamma_sdk-1.0.0.dist-info/METADATA
polymarket_gamma_sdk-1.0.0.dist-info/WHEEL
polymarket_gamma_sdk-1.0.0.dist-info/top_level.txt
polymarket_gamma_sdk-1.0.0.dist-info/RECORD
