Metadata-Version: 2.4
Name: polymarket-gamma-sdk
Version: 1.0.0
Summary: Asynchronous Python SDK for Polymarket's Gamma API
Home-page: https://github.com/mateo-bivol/polymarket-gamma-sdk
Author: Mateo Bivol
Author-email: mateo.bivol@mail.utoronto.ca
License: MIT
Classifier: Programming Language :: Python :: 3
Classifier: License :: OSI Approved :: MIT License
Classifier: Operating System :: OS Independent
Requires-Python: >=3.8
License-File: LICENSE
Requires-Dist: httpx>=0.24.0
Requires-Dist: pydantic>=2.0.0
Dynamic: author
Dynamic: author-email
Dynamic: classifier
Dynamic: description
Dynamic: description-content-type
Dynamic: home-page
Dynamic: license
Dynamic: license-file
Dynamic: requires-dist
Dynamic: requires-python
Dynamic: summary
